pyulgresample/__init__.py
pyulgresample/loginfo.py
pyulgresample/mathpandas.py
pyulgresample/ulogconv.py
pyulgresample/ulogdataframe.py
pyulgresample-0.0.5.dist-info/LICENSE
pyulgresample-0.0.5.dist-info/WHEEL
pyulgresample-0.0.5.dist-info/METADATA
pyulgresample-0.0.5.dist-info/RECORD
