Metadata-Version: 2.1
Name: pyulgresample
Version: 0.0.5
Summary: pyulgresample.
Home-page: https://github.com/YUNEEC/pyulgresample
License: UNKNOWN
Author: Dennis Mannhart
Author-email: dennis@yuneecresearch.com
Requires-Python: >=3.6
Classifier: Development Status :: 3 - Alpha
Classifier: Intended Audience :: Developers
Classifier: Topic :: Software Development :: Libraries :: Python Modules
Classifier: Programming Language :: Python :: 3
Classifier: License :: OSI Approved :: BSD License
Classifier: Operating System :: OS Independent
Requires-Dist: numpy (>= 1.15.3)
Requires-Dist: pandas (>= 0.23.4)
Requires-Dist: pyulog (>= 0.6.0)
Requires-Dist: utm (>= 0.4.2)
Requires-Dist: transforms3d
Requires-Dist: flake8; extra == "requires"
Requires-Dist: pre-commit; extra == "requires"
Requires-Dist: pytest; extra == "test"
Provides-Extra: .none
Provides-Extra: requires
Provides-Extra: test
